README.rst
setup.cfg
setup.py
bin/eventlogging-consumer
bin/eventlogging-devserver
bin/eventlogging-forwarder
bin/eventlogging-multiplexer
bin/eventlogging-processor
bin/eventlogging-reporter
eventlogging/__init__.py
eventlogging/compat.py
eventlogging/crypto.py
eventlogging/factory.py
eventlogging/handlers.py
eventlogging/jrm.py
eventlogging/parse.py
eventlogging/schema.py
eventlogging/streams.py
eventlogging/utils.py
eventlogging.egg-info/PKG-INFO
eventlogging.egg-info/SOURCES.txt
eventlogging.egg-info/dependency_links.txt
eventlogging.egg-info/not-zip-safe
eventlogging.egg-info/requires.txt
eventlogging.egg-info/top_level.txt