Metadata-Version: 1.1
Name: eventlogging
Version: 0.8
Summary: Server-side component of EventLogging MediaWiki extension.
Home-page: https://www.mediawiki.org/wiki/Extension:EventLogging
Author: Ori Livneh
Author-email: ori@wikimedia.org
License: GPL
Platform: UNKNOWN
Classifier: Development Status :: 4 - Beta
Classifier: License :: OSI Approved :: GNU General Public License v2 or later (GPLv2+)
Classifier: Programming Language :: JavaScript
Classifier: Programming Language :: PHP
Classifier: Programming Language :: Python :: 2.7
Classifier: Programming Language :: Python :: 3.3
Classifier: Topic :: Database
Classifier: Topic :: Scientific/Engineering :: Interface Engine/Protocol Translator
Classifier: Topic :: Software Development :: Object Brokering
